phonexia_keyword_spotting_client.py
phonexia_keyword_spotting_client-2.1.1.dist-info/METADATA
phonexia_keyword_spotting_client-2.1.1.dist-info/WHEEL
phonexia_keyword_spotting_client-2.1.1.dist-info/entry_points.txt
phonexia_keyword_spotting_client-2.1.1.dist-info/top_level.txt
phonexia_keyword_spotting_client-2.1.1.dist-info/RECORD
