Metadata-Version: 2.4
Name: phonexia-keyword-spotting-client
Version: 2.1.1
Summary: Keyword Spotting Client
Author-email: Phonexia <info@phonexia.com>
Keywords: keyword-spotting,audio,voice,speech,search,grpc
Requires-Python: >=3.9
Requires-Dist: more-itertools>=10.6.0
Requires-Dist: phonexia-grpc>=2.27.1
Requires-Dist: numpy>=2.0.0; python_version >= "3.12"
Requires-Dist: numpy<2.0.0; python_version < "3.12"
Requires-Dist: typer>=0.16.0
Requires-Dist: soundfile>=0.13.0
